corha/__init__.py
corha/corha.py
corha-0.3.0.dist-info/LICENSE
corha-0.3.0.dist-info/METADATA
corha-0.3.0.dist-info/WHEEL
corha-0.3.0.dist-info/top_level.txt
corha-0.3.0.dist-info/RECORD
